{
	"version": "7",
	"dialect": "postgresql",
	"entries": [
		{
			"idx": 0,
			"version": "7",
			"when": 1758856412323,
			"tag": "0000_colorful_ted_forrester",
			"breakpoints": true
		},
		{
			"idx": 1,
			"version": "7",
			"when": 1758894246863,
			"tag": "0001_thankful_warbird",
			"breakpoints": true
		},
		{
			"idx": 2,
			"version": "7",
			"when": 1758927275789,
			"tag": "0002_wild_betty_brant",
			"breakpoints": true
		},
		{
			"idx": 3,
			"version": "7",
			"when": 1758932201561,
			"tag": "0003_round_spencer_smythe",
			"breakpoints": true
		}
	]
}
